odoo10_addon_l10n_fi_business_code-10.0.1.2.0.99.dev1-py2.7-nspkg.pth
odoo/addons/l10n_fi_business_code/README.rst
odoo/addons/l10n_fi_business_code/__init__.py
odoo/addons/l10n_fi_business_code/__manifest__.py
odoo/addons/l10n_fi_business_code/data/res_partner_id_category.xml
odoo/addons/l10n_fi_business_code/i18n/fi.po
odoo/addons/l10n_fi_business_code/i18n/l10n_fi_business_code.pot
odoo/addons/l10n_fi_business_code/models/__init__.py
odoo/addons/l10n_fi_business_code/models/res_partner.py
odoo/addons/l10n_fi_business_code/static/description/icon.png
odoo/addons/l10n_fi_business_code/views/res_partner.xml
odoo10_addon_l10n_fi_business_code-10.0.1.2.0.99.dev1.dist-info/METADATA
odoo10_addon_l10n_fi_business_code-10.0.1.2.0.99.dev1.dist-info/RECORD
odoo10_addon_l10n_fi_business_code-10.0.1.2.0.99.dev1.dist-info/WHEEL
odoo10_addon_l10n_fi_business_code-10.0.1.2.0.99.dev1.dist-info/namespace_packages.txt
odoo10_addon_l10n_fi_business_code-10.0.1.2.0.99.dev1.dist-info/top_level.txt
